main.py
setup.py
tarseir.egg-info/PKG-INFO
tarseir.egg-info/SOURCES.txt
tarseir.egg-info/dependency_links.txt
tarseir.egg-info/requires.txt
tarseir.egg-info/top_level.txt